xkey/__about__.py
xkey/__init__.py
xkey/cli.py
xkey/exception.py
xkey/sysex/__init__.py
xkey/sysex/constant.py
xkey/sysex/parser.py
xkey/sysex/novation/__init__.py
xkey/sysex/novation/codec.py
xkey/sysex/novation/constant.py
xkey/sysex/novation/message.py
xkey-0.1.0.dist-info/LICENSE
xkey-0.1.0.dist-info/METADATA
xkey-0.1.0.dist-info/WHEEL
xkey-0.1.0.dist-info/entry_points.txt
xkey-0.1.0.dist-info/top_level.txt
xkey-0.1.0.dist-info/RECORD
