Metadata-Version: 2.1
Name: xkey
Version: 0.1.0
Summary: Novation SysEx utilities.
Author-email: Peter Adkins <peter@sunkenlab.com>
License: AGPL-3.0
Classifier: Programming Language :: Python :: 3
Requires-Python: >=3.7
License-File: LICENSE
Provides-Extra: tests
Requires-Dist: black ; extra == 'tests'
Requires-Dist: coverage ; extra == 'tests'
Requires-Dist: ruff ; extra == 'tests'
Requires-Dist: types-setuptools ; extra == 'tests'
Requires-Dist: isort ; extra == 'tests'
Requires-Dist: mypy ; extra == 'tests'
Requires-Dist: pip-tools ; extra == 'tests'
Requires-Dist: mock ; extra == 'tests'
Requires-Dist: pytest ; extra == 'tests'
Requires-Dist: pytest-cov ; extra == 'tests'
Requires-Dist: responses ; extra == 'tests'
Requires-Dist: tox ; extra == 'tests'
Requires-Dist: sphinx ; extra == 'tests'
Requires-Dist: furo ; extra == 'tests'
